xss_utils/__init__.py
xss_utils/apps.py
xss_utils/mako/__init__.py
xss_utils/templatetags/__init__.py
xss_utils/templatetags/django_markup.py
xss_utils/tests/__init__.py
xss_utils/tests/test_templatetags.py
xss_utils-0.8.0.dist-info/licenses/AUTHORS
xss_utils-0.8.0.dist-info/licenses/LICENSE
xss_utils-0.8.0.dist-info/METADATA
xss_utils-0.8.0.dist-info/WHEEL
xss_utils-0.8.0.dist-info/top_level.txt
xss_utils-0.8.0.dist-info/RECORD
